khulnasoft_pandas/__init__.py
khulnasoft_pandas/_nbdev.py
khulnasoft_pandas/data.py
khulnasoft_pandas/data_cloud.py
khulnasoft_pandas/utils.py
khulnasoft_pandas/wrangle.py
khulnasoft_pandas-0.0.46.dist-info/LICENSE
khulnasoft_pandas-0.0.46.dist-info/METADATA
khulnasoft_pandas-0.0.46.dist-info/WHEEL
khulnasoft_pandas-0.0.46.dist-info/top_level.txt
khulnasoft_pandas-0.0.46.dist-info/RECORD
