Metadata-Version: 2.1
Name: khulnasoft-pandas
Version: 0.0.46
Summary: A helper library for pulling data from khulnasoft into a pandas dataframe.
Home-page: https://github.com/khulnasoft/khulnasoft-pandas/tree/master/
Author: KhulnaSoft DevOps
Author-email: admin@khulnasoft.com
License: Apache Software License 2.0
Keywords: khulnasoft pandas
Classifier: Development Status :: 3 - Alpha
Classifier: Intended Audience :: Developers
Classifier: License :: OSI Approved :: Apache Software License
Classifier: Natural Language :: English
Classifier: Programming Language :: Python :: 3.6
Classifier: Programming Language :: Python :: 3.7
Classifier: Programming Language :: Python :: 3.8
Requires-Python: >=3.6
License-File: LICENSE
Requires-Dist: pandas >=1.0.4
Requires-Dist: asks >=2.4.12
Requires-Dist: trio >=0.18.0
Requires-Dist: requests >=2.25.1
